turkishfullname
